{
  "source": "https://www.instagram.com/koshichhyang/",
  "note": "Updated from community-comments-export.json via merge_community_comments.py",
  "posts": {
    "hero": {
      "thumb": "hero.jpg",
      "caption": "UK launch / brand intro"
    },
    "pour": {
      "thumb": "pour.jpg",
      "caption": "Pour reel"
    },
    "brew": {
      "thumb": "brew.jpg",
      "caption": "Fermentation / brew reel"
    },
    "product-1": {
      "thumb": "product-1.jpg",
      "caption": "Heritage / Gurkha story"
    },
    "product-2": {
      "thumb": "product-2.jpg",
      "caption": "Bottle & branding"
    },
    "product-3": {
      "thumb": "product-3.jpg",
      "caption": "Terroir / landscape"
    },
    "event": {
      "thumb": "event.jpg",
      "caption": "Launch tasting / event"
    },
    "collection-1": {
      "thumb": "collection/classic-chhyang.jpg",
      "caption": "Classic chhyang"
    },
    "collection-2": {
      "thumb": "collection/spiced-chhyang.jpg",
      "caption": "Spiced blend"
    },
    "collection-3": {
      "thumb": "collection/berry-fusion-chhyang.jpg",
      "caption": "Berry fusion"
    },
    "collection-4": {
      "thumb": "collection/citrus-zest-chhyang.jpg",
      "caption": "Citrus zest"
    },
    "collection-5": {
      "thumb": "collection/ginger-spice-chhyang.jpg",
      "caption": "Ginger spice"
    },
    "collection-6": {
      "thumb": "collection/aged-heritage-chhyang.jpg",
      "caption": "Aged heritage"
    },
    "heritage-process": {
      "thumb": "heritage-band.jpg",
      "caption": "Heritage rice ferment"
    }
  },
  "comments": [
    {
      "handle": "mychi_pham",
      "name": "mychi_pham",
      "post": "collection-4",
      "text": "So excited!!",
      "when": "on Instagram"
    },
    {
      "handle": "seresastore",
      "name": "seresastore",
      "post": "collection-5",
      "text": "this is amazing, I'm so excited for you!!!",
      "when": "on Instagram"
    },
    {
      "handle": "geelagirl",
      "name": "geelagirl",
      "post": "heritage-process",
      "text": "yayyy!!!!",
      "when": "on Instagram"
    },
    {
      "handle": "uswizzyy",
      "name": "uswizzyy",
      "post": "product-2",
      "text": "😍😍😍",
      "when": "on Instagram"
    },
    {
      "handle": "alvin.khatri",
      "name": "alvin.khatri",
      "post": "collection-6",
      "text": "I really like the taste of koshichhyang which was really gives Nepali taste and thank you so much for koshichhyang teams.",
      "when": "on Instagram"
    },
    {
      "handle": "serima.s",
      "name": "serima.s",
      "post": "hero",
      "text": "EYYYYY!! drop us a few test bottles then 😛",
      "when": "on Instagram"
    },
    {
      "handle": "dolmayuki",
      "name": "dolmayuki",
      "post": "product-3",
      "text": "So lucky to see the journey 🤞✨",
      "when": "on Instagram"
    },
    {
      "handle": "mychi_pham",
      "name": "mychi_pham",
      "post": "heritage-process",
      "text": "booked and busyyy 👏👏",
      "when": "on Instagram"
    },
    {
      "handle": "geelagirl",
      "name": "geelagirl",
      "post": "event",
      "text": "yayyy!!!!",
      "when": "on Instagram"
    }
  ]
}
